coptic/__init__.py
coptic/core/__init__.py
coptic/core/arima_model.py
coptic/core/base_model.py
coptic/core/prophet_model.py
coptic/core/rf_model.py
coptic/core/xgb_model.py
coptic/preprocessing/__init__.py
coptic/preprocessing/cleaner.py
coptic/preprocessing/features.py
coptic/utils/__init__.py
coptic/utils/metrics.py
coptic/utils/plot.py
coptic-0.1.0.dist-info/licenses/LICENSE
coptic-0.1.0.dist-info/METADATA
coptic-0.1.0.dist-info/WHEEL
coptic-0.1.0.dist-info/top_level.txt
coptic-0.1.0.dist-info/RECORD
