Metadata-Version: 2.4
Name: coptic
Version: 0.1.0
Summary: Advanced time series forecasting library with multiple algorithms
Home-page: https://github.com/yourusername/coptic
Author: Coptic Team
Author-email: Coptic Team <contact@coptic-forecasting.com>
License: MIT
Project-URL: Homepage, https://github.com/yourusername/coptic
Project-URL: Documentation, https://coptic.readthedocs.io
Project-URL: Repository, https://github.com/yourusername/coptic.git
Project-URL: Bug Tracker, https://github.com/yourusername/coptic/issues
Keywords: time-series,forecasting,machine-learning,prophet,arima,xgboost,random-forest
Classifier: Development Status :: 4 - Beta
Classifier: Intended Audience :: Science/Research
Classifier: Intended Audience :: Developers
Classifier: Topic :: Scientific/Engineering :: Artificial Intelligence
Classifier: License :: OSI Approved :: MIT License
Classifier: Programming Language :: Python :: 3
Classifier: Programming Language :: Python :: 3.7
Classifier: Programming Language :: Python :: 3.8
Classifier: Programming Language :: Python :: 3.9
Classifier: Programming Language :: Python :: 3.10
Classifier: Programming Language :: Python :: 3.11
Requires-Python: >=3.7
License-File: LICENSE
Requires-Dist: numpy>=1.20.0
Requires-Dist: pandas>=1.2.0
Requires-Dist: scikit-learn>=0.24.0
Requires-Dist: matplotlib>=3.3.0
Requires-Dist: xgboost>=1.3.0
Requires-Dist: prophet>=1.0.0
Requires-Dist: pmdarima>=1.8.0
Requires-Dist: statsmodels>=0.12.0
Provides-Extra: dev
Requires-Dist: pytest>=6.0; extra == "dev"
Requires-Dist: pytest-cov>=2.0; extra == "dev"
Requires-Dist: black>=21.0; extra == "dev"
Requires-Dist: flake8>=3.9; extra == "dev"
Requires-Dist: sphinx>=4.0; extra == "dev"
Requires-Dist: mypy>=0.900; extra == "dev"
Requires-Dist: jupyter>=1.0; extra == "dev"
Requires-Dist: notebook>=6.0; extra == "dev"
Provides-Extra: docs
Requires-Dist: sphinx>=4.0; extra == "docs"
Requires-Dist: sphinx-rtd-theme>=0.5.0; extra == "docs"
Requires-Dist: sphinxcontrib-napoleon>=0.7; extra == "docs"
Provides-Extra: examples
Requires-Dist: jupyter>=1.0; extra == "examples"
Requires-Dist: seaborn>=0.11.0; extra == "examples"
Requires-Dist: plotly>=5.0; extra == "examples"
Dynamic: author
Dynamic: home-page
Dynamic: license-file
Dynamic: requires-python
